hypyp/__init__.py
hypyp/analyses.py
hypyp/data/Basehead.obj
hypyp/ext/__init__.py
hypyp/ext/mpl3d/__init__.py
hypyp/ext/mpl3d/camera.py
hypyp/ext/mpl3d/glm.py
hypyp/ext/mpl3d/lighting.py
hypyp/ext/mpl3d/mesh.py
hypyp/ext/mpl3d/trackball.py
hypyp/fnirs/__init__.py
hypyp/fnirs/channel_roi.py
hypyp/fnirs/data_browser.py
hypyp/fnirs/dyad.py
hypyp/fnirs/legacy/fnirs_tools.py
hypyp/fnirs/preprocessor/base_preprocessor.py
hypyp/fnirs/preprocessor/base_step.py
hypyp/fnirs/preprocessor/implementations/cedalion_preprocessor.py
hypyp/fnirs/preprocessor/implementations/mne_preprocessor_as_is.py
hypyp/fnirs/preprocessor/implementations/mne_preprocessor_raw_to_haemo.py
hypyp/fnirs/preprocessor/implementations/mne_step.py
hypyp/fnirs/recording.py
hypyp/fnirs/study.py
hypyp/io.py
hypyp/mvarica.py
hypyp/plots.py
hypyp/prep.py
hypyp/profiling.py
hypyp/shiny/study_viewer.py
hypyp/shiny/wavelet_explorer.py
hypyp/signal.py
hypyp/stats.py
hypyp/utils.py
hypyp/viz.py
hypyp/wavelet/__init__.py
hypyp/wavelet/base_wavelet.py
hypyp/wavelet/coherence_data_frame.py
hypyp/wavelet/cwt.py
hypyp/wavelet/implementations/matlab_wavelet.py
hypyp/wavelet/implementations/pycwt_wavelet.py
hypyp/wavelet/implementations/pywavelets_wavelet.py
hypyp/wavelet/pair_signals.py
hypyp/wavelet/wtc.py
hypyp/xdf/__init__.py
hypyp/xdf/xdf_import.py
hypyp/xdf/xdf_stream.py
hypyp-0.5.0b18.dist-info/METADATA
hypyp-0.5.0b18.dist-info/WHEEL
hypyp-0.5.0b18.dist-info/licenses/LICENSE
hypyp-0.5.0b18.dist-info/RECORD
