Metadata-Version: 2.4
Name: hypyp
Version: 0.5.0b18
Summary: The Hyperscanning Python Pipeline.
License-Expression: BSD-3-Clause
License-File: LICENSE
Keywords: hyperscanning,neuroscience,pipeline,statistics,visualization
Requires-Python: >=3.10,<3.14
Classifier: Development Status :: 4 - Beta
Classifier: Topic :: Scientific/Engineering
Requires-Dist: autoreject (>=0.4.3)
Requires-Dist: black (>=25.1.0)
Requires-Dist: certifi (>=2022.12.07)
Requires-Dist: importlib-resources (>=6.0.0)
Requires-Dist: matplotlib (>=3.7.2)
Requires-Dist: meshio (>=5.3.4)
Requires-Dist: mistune (>=2.0.4)
Requires-Dist: mne (>=1.3)
Requires-Dist: mne-connectivity (>=0.7.0)
Requires-Dist: numpy (>=2.2.3)
Requires-Dist: pandas (>=2.0.3)
Requires-Dist: pillow (>=11.3.0)
Requires-Dist: pyarrow (>=20.0.0)
Requires-Dist: pywavelets (>=1.8.0)
Requires-Dist: pyxdf (>=1.17.0)
Requires-Dist: requests (>=2.32.4)
Requires-Dist: scikit-image (>=0.25.2)
Requires-Dist: scipy (>=1.11.1,<1.17.0)
Requires-Dist: seaborn (>=0.13.2)
Requires-Dist: snirf (>=0.8.0)
Requires-Dist: statsmodels (>=0.14.4)
Requires-Dist: tqdm (>=4.46.0)
Requires-Dist: urllib3 (>=2.5.0)
Project-URL: Documentation, https://hypyp.readthedocs.io
Project-URL: Homepage, https://github.com/ppsp-team/HyPyP
Project-URL: Repository, https://github.com/ppsp-team/HyPyP
